.gitignore
CHANGELOG.rst
COPYING.rst
GNUmakefile
LICENSE
NEWS
NOTES
README.rst
distribute_setup.py
ez_setup.py
setup.cfg
setup.py
tst.py
docs/Makefile
docs/source/conf.py
docs/source/index.rst
rcmp/__init__.py
rcmp/main.py
rcmp/tests.py
rcmp.egg-info/PKG-INFO
rcmp.egg-info/SOURCES.txt
rcmp.egg-info/dependency_links.txt
rcmp.egg-info/entry_points.txt
rcmp.egg-info/requires.txt
rcmp.egg-info/top_level.txt
testfiles/Makefile.am
testfiles/README
testfiles/configure.ac
testfiles/main.c
testfiles/black/x.map
testfiles/left/Makefile
testfiles/left/Makefile.in.bz2
testfiles/left/Makefile.in.gz
testfiles/left/Makefile.in.xz
testfiles/left/archive.a
testfiles/left/config.log
testfiles/left/config.status
testfiles/left/cpiofile.cpio
testfiles/left/empty
testfiles/left/main.o
testfiles/left/tarfile.tar
testfiles/left/yo.bz2.bz2.bz2
testfiles/left/yo.gz.gz.gz
testfiles/left/yo.xz.xz.xz
testfiles/left/zipfile.zip
testfiles/red/x.map
testfiles/right/Makefile
testfiles/right/Makefile.in.bz2
testfiles/right/Makefile.in.gz
testfiles/right/Makefile.in.xz
testfiles/right/archive.a
testfiles/right/config.log
testfiles/right/config.status
testfiles/right/cpiofile.cpio
testfiles/right/empty
testfiles/right/main.o
testfiles/right/tarfile.tar
testfiles/right/yo.bz2.bz2.bz2
testfiles/right/yo.gz.gz.gz
testfiles/right/yo.xz.xz.xz
testfiles/right/zipfile.zip