Metadata-Version: 1.1
Name: rcmp
Version: 0.8
Summary: A flexible and extendable file and directory comparison tool.
Home-page: https://github.com/rich-pixley/rcmp
Author: K Richard Pixley
Author-email: rich@noir.com
License: APACHE
Download-URL: https://api.github.com/repos/rich-pixley/rcmp/tarball
Platform: UNKNOWN
Classifier: Development Status :: 2 - Pre-Alpha
Classifier: Environment :: Console
Classifier: Intended Audience :: Developers
Classifier: License :: OSI Approved :: Apache Software License
Classifier: Natural Language :: English
Classifier: Operating System :: OS Independent
Classifier: Programming Language :: Python :: 2.7
Classifier: Programming Language :: Python
Classifier: Topic :: Software Development :: Libraries :: Python Modules
Classifier: Topic :: Software Development :: Testing
Classifier: Topic :: Utilities
Provides: rcmp
